{
  "version": "7",
  "dialect": "sqlite",
  "entries": [
    {
      "idx": 0,
      "version": "6",
      "when": 1739836699379,
      "tag": "0000_remarkable_moon_knight",
      "breakpoints": true
    },
    {
      "idx": 1,
      "version": "6",
      "when": 1739867138545,
      "tag": "0001_typical_ricochet",
      "breakpoints": true
    },
    {
      "idx": 2,
      "version": "6",
      "when": 1739867309761,
      "tag": "0002_fine_wendell_vaughn",
      "breakpoints": true
    },
    {
      "idx": 3,
      "version": "6",
      "when": 1739868731861,
      "tag": "0003_open_gateway",
      "breakpoints": true
    },
    {
      "idx": 4,
      "version": "6",
      "when": 1739877149360,
      "tag": "0004_workable_brood",
      "breakpoints": true
    },
    {
      "idx": 5,
      "version": "6",
      "when": 1740155648399,
      "tag": "0005_unique_thunderball",
      "breakpoints": true
    }
  ]
}